{
  "headline": "Sugar Land Dominates, a Tie Steals the Spotlight, and Beer League Baseball Is Back",
  "subheadline": "Week 1 delivered blowouts, a dramatic stalemate, and early signals about which rosters are built to last.",
  "body": "There is something clarifying about Opening Week in beer league fantasy baseball. The rosters are fresh, the optimism is universal, and then the games actually get played \u2014 and you find out rather quickly who spent the offseason making smart decisions and who showed up hoping last year's magic would carry over. Week 1 of the Miller Lite Beer League Baseball season did not disappoint on any of those fronts. It gave us a dominant performance that should send a message to the rest of the field, a genuinely surprising blowout or two, and \u2014 perhaps most intriguingly \u2014 a tie that may loom larger in October than it does right now in the first week of April.\n\nThe tie between **General Hospital** and the **Wonder Wharf Wonderdogs**, finishing at 4.0\u20134.0, is the kind of result that looks minor on a Tuesday morning and catastrophic in a one-game playoff scenario. Both managers will move on, chalk it up to bad luck, and point to the long season ahead. They are not wrong to do so. But history in formats like this one tells us that split points have a way of resurfacing at the worst possible moment. The **Wonderdogs** in particular \u2014 a team that many around the league expected to contend \u2014 will want to study the tape on this one. A full point left on the table in Week 1 is a full point you cannot get back.\n\n## The Performances That Defined the Week\n\nLet's start with the obvious: **Sugar Land Skeeters** won their opener 9.0\u20131.0 over the **Riverside Roughnecks**, and that margin demands attention. A nine-to-one result in this format is not a win \u2014 it is a statement. The **Skeeters** enter 2025 as a club that has clearly invested in production across multiple lineup slots, and this performance suggests the depth is real, not theoretical. The **Roughnecks**, for their part, mustered just a single point \u2014 a performance that raises genuine questions about whether their roster construction is sound heading into a long season.\n\n**BaseballPro77** also came out swinging, rolling past the **Canberra Wombats** 8.0\u20132.0 in a result that reinforces what scouts around the league have been saying for weeks: this is a lineup with legitimate firepower. The **Wombats** have historically been a streaky club, capable of stringing together strong weeks, but getting out-pointed by six in a season opener is not the trajectory any team wants to establish.\n\nOn the other end of the competitive spectrum, **Athletic Park Dragons** edged the **Hiroshima Radiation** 5.0\u20134.0 in what was the closest traditional result of the week outside the tie. Both clubs should feel reasonably encouraged \u2014 the **Radiation** showed they can compete, and the **Dragons** showed they can close \u2014 but a one-point margin in Week 1 is a reminder that neither team has separated itself from the pack yet.\n\n**North Correa** handled the **Wisconsin Rapids Reapers** 7.0\u20133.0 in a result that deserves more conversation than it may receive. The **Reapers** were considered a potential sleeper by several analysts heading into the year, and a three-point week against a quality opponent suggests their offseason additions may not have translated the way the front office anticipated.\n\n## Standout Performances Worth Noting\n\nThe **Albuquerque Bombers** took down the **Abbotsford-Colby Twins** 6.0\u20134.0 in a measured, professional victory \u2014 the kind of win that does not make headlines but tells you something about roster construction. The **Bombers** did not rely on a single monster category; they distributed their points across the lineup, which is the signature of a well-built team rather than one riding a hot hand. The **Benchwarmers**, meanwhile, dispatched the **Buttville Skidmarks** 7.0\u20133.0 \u2014 a team name that, frankly, may be the most accurate piece of scouting in the entire league right now.\n\n## Standings & Race \u2014 What Week 1 Actually Means\n\nThe standings currently reflect only pre-season rankings with wins and losses yet to be formally tabulated, which means the playoff picture is genuinely wide open. What we do know is this: the teams that scored nine, eight, and seven points in Week 1 \u2014 **Sugar Land**, **BaseballPro77**, and **North Correa** and **Benchwarmers** respectively \u2014 have set an early benchmark. The clubs that finished at four points or below \u2014 particularly **Riverside**, **Canberra**, and the two teams that tied \u2014 are already operating without margin for error. In a format where every week is a data point, starting 0.5 points behind the leaders is not a crisis. Starting there with roster questions unanswered is.\n\n## Looking Ahead\n\nWeek 2 will tell us considerably more about which first-week performances were signal and which were noise. Keep a close eye on whether the **Hiroshima Radiation** can rebound after their one-point loss to the **Dragons** \u2014 a competitive club that loses close should respond, and how they do will define their season arc early. The **Wonder Wharf Wonderdogs** cannot afford another split; they need a full win to reassert themselves as contenders. And **Sugar Land**? They are the team everyone else is measuring themselves against right now, whether they admit it or not.",
  "generated_at": "2026-03-30T15:09:32.212733",
  "week": 1,
  "writer_key": "olney",
  "writer_name": "Buster Olney",
  "writer_outlet": "ESPN",
  "is_playoff": false,
  "is_championship": false
}